llpy/__init__.py
llpy/types.py
llpy/classes/base/types.py
llpy/classes/base/directionangle/__init__.py
llpy/classes/base/directionangle/__init__.pyi
llpy/classes/base/enumdefine/__init__.pyi
llpy/classes/base/format/__init__.py
llpy/classes/base/format/__init__.pyi
llpy/classes/base/pos/__init__.py
llpy/classes/base/pos/__init__.pyi
llpy/classes/block/__init__.py
llpy/classes/block/__init__.pyi
llpy/classes/block/entity/__init__.py
llpy/classes/block/entity/__init__.pyi
llpy/classes/command/__init__.py
llpy/classes/command/__init__.pyi
llpy/classes/command/types.py
llpy/classes/command/enums/__init__.py
llpy/classes/command/enums/__init__.pyi
llpy/classes/command/origin/__init__.py
llpy/classes/command/origin/__init__.pyi
llpy/classes/command/output/__init__.py
llpy/classes/command/output/__init__.pyi
llpy/classes/config/types.py
llpy/classes/config/ini/__init__.py
llpy/classes/config/ini/__init__.pyi
llpy/classes/config/json/__init__.py
llpy/classes/config/json/__init__.pyi
llpy/classes/container/__init__.py
llpy/classes/container/__init__.pyi
llpy/classes/data/__init__.py
llpy/classes/data/__init__.pyi
llpy/classes/data/types.py
llpy/classes/db/types.py
llpy/classes/db/dbsession/__init__.py
llpy/classes/db/dbsession/__init__.pyi
llpy/classes/db/dbstmt/__init__.py
llpy/classes/db/dbstmt/__init__.pyi
llpy/classes/db/kvdb/__init__.py
llpy/classes/db/kvdb/__init__.pyi
llpy/classes/entity/__init__.py
llpy/classes/entity/__init__.pyi
llpy/classes/entity/types.py
llpy/classes/entity/damagecause/__init__.py
llpy/classes/entity/damagecause/__init__.pyi
llpy/classes/file/__init__.py
llpy/classes/file/__init__.pyi
llpy/classes/file/types.py
llpy/classes/form/custom/__init__.py
llpy/classes/form/custom/__init__.pyi
llpy/classes/form/simple/__init__.py
llpy/classes/form/simple/__init__.pyi
llpy/classes/i18n/__init__.py
llpy/classes/i18n/__init__.pyi
llpy/classes/i18n/types.py
llpy/classes/item/__init__.py
llpy/classes/item/__init__.pyi
llpy/classes/ll/__init__.py
llpy_helper_lib-2.13.1.post1.dist-info/LICENSE
llpy_helper_lib-2.13.1.post1.dist-info/METADATA
llpy_helper_lib-2.13.1.post1.dist-info/WHEEL
llpy_helper_lib-2.13.1.post1.dist-info/top_level.txt
llpy_helper_lib-2.13.1.post1.dist-info/RECORD
