Metadata-Version: 2.2
Name: llpy-helper-lib
Version: 2.13.1.post1
Summary: A typing & util lib for LLSE Python runtime
Author-email: LgCookie <lgc2333@126.com>
License: MIT
Requires-Python: >=3.10
License-File: LICENSE
Requires-Dist: typing-extensions>=4.5.0
Provides-Extra: dev
Requires-Dist: setuptools>=76.0.0; extra == "dev"
Requires-Dist: pip>=25.0.1; extra == "dev"
Requires-Dist: basedpyright>=1.28.1; extra == "dev"
Requires-Dist: ruff>=0.11.0; extra == "dev"
